mcp_code_indexer/__init__.py
mcp_code_indexer/__main__.py
mcp_code_indexer/ask_handler.py
mcp_code_indexer/claude_api_handler.py
mcp_code_indexer/cleanup_manager.py
mcp_code_indexer/commands/__init__.py
mcp_code_indexer/commands/makelocal.py
mcp_code_indexer/data/stop_words_english.txt
mcp_code_indexer/database/__init__.py
mcp_code_indexer/database/connection_health.py
mcp_code_indexer/database/database.py
mcp_code_indexer/database/database_factory.py
mcp_code_indexer/database/exceptions.py
mcp_code_indexer/database/models.py
mcp_code_indexer/database/path_resolver.py
mcp_code_indexer/database/retry_executor.py
mcp_code_indexer/deepask_handler.py
mcp_code_indexer/error_handler.py
mcp_code_indexer/file_scanner.py
mcp_code_indexer/git_hook_handler.py
mcp_code_indexer/logging_config.py
mcp_code_indexer/main.py
mcp_code_indexer/middleware/__init__.py
mcp_code_indexer/middleware/auth.py
mcp_code_indexer/middleware/error_middleware.py
mcp_code_indexer/middleware/logging.py
mcp_code_indexer/middleware/security.py
mcp_code_indexer/migrations/001_initial.sql
mcp_code_indexer/migrations/002_performance_indexes.sql
mcp_code_indexer/migrations/003_project_overviews.sql
mcp_code_indexer/migrations/004_remove_branch_dependency.sql
mcp_code_indexer/migrations/005_remove_git_remotes.sql
mcp_code_indexer/migrations/006_vector_mode.sql
mcp_code_indexer/query_preprocessor.py
mcp_code_indexer/server/__init__.py
mcp_code_indexer/server/mcp_server.py
mcp_code_indexer/tiktoken_cache/9b5ad71b2ce5302211f9c61530b329a4922fc6a4
mcp_code_indexer/token_counter.py
mcp_code_indexer/tools/__init__.py
mcp_code_indexer/transport/__init__.py
mcp_code_indexer/transport/base.py
mcp_code_indexer/transport/http_transport.py
mcp_code_indexer/transport/stdio_transport.py
mcp_code_indexer/vector_mode/__init__.py
mcp_code_indexer/vector_mode/chunking/__init__.py
mcp_code_indexer/vector_mode/chunking/ast_chunker.py
mcp_code_indexer/vector_mode/chunking/chunk_optimizer.py
mcp_code_indexer-4.2.15.dist-info/LICENSE
mcp_code_indexer-4.2.15.dist-info/METADATA
mcp_code_indexer-4.2.15.dist-info/WHEEL
mcp_code_indexer-4.2.15.dist-info/entry_points.txt
mcp_code_indexer-4.2.15.dist-info/RECORD
