Metadata-Version: 2.3
Name: mcp-code-indexer
Version: 4.2.15
Summary: MCP server that tracks file descriptions across codebases, enabling AI agents to efficiently navigate and understand code through searchable summaries and token-aware overviews.
License: MIT
Keywords: mcp,model-context-protocol,code-indexer,ai-tools,codebase-navigation,file-descriptions,llm-tools
Author: MCP Code Indexer Contributors
Maintainer: MCP Code Indexer Contributors
Requires-Python: >=3.10,<3.14
Classifier: Development Status :: 5 - Production/Stable
Classifier: Environment :: Console
Classifier: Framework :: AsyncIO
Classifier: Intended Audience :: Developers
Classifier: License :: OSI Approved :: MIT License
Classifier: Operating System :: OS Independent
Classifier: Programming Language :: Python :: 3
Classifier: Programming Language :: Python :: 3.10
Classifier: Programming Language :: Python :: 3.11
Classifier: Programming Language :: Python :: 3.12
Classifier: Programming Language :: Python :: 3.13
Classifier: Programming Language :: Python :: 3.9
Classifier: Topic :: Scientific/Engineering :: Artificial Intelligence
Classifier: Topic :: Software Development
Classifier: Topic :: Software Development :: Libraries :: Python Modules
Classifier: Typing :: Typed
Requires-Dist: aiofiles (==23.2.0)
Requires-Dist: aiohttp (>=3.8.0)
Requires-Dist: aiosqlite (==0.19.0)
Requires-Dist: fastapi (>=0.104.0)
Requires-Dist: gitignore-parser (==0.1.11)
Requires-Dist: importlib-metadata (>=1.0.0) ; python_version < "3.8"
Requires-Dist: mcp (>=1.9.0)
Requires-Dist: pydantic (>=2.8.0)
Requires-Dist: python-multipart (>=0.0.6)
Requires-Dist: pyyaml (>=6.0)
Requires-Dist: tenacity (>=8.0.0)
Requires-Dist: tiktoken (>=0.9.0)
Requires-Dist: tomli (>=1.2.0) ; python_version < "3.11"
Requires-Dist: tree-sitter (>=0.25.0)
Requires-Dist: turbopuffer (>=0.6.0)
Requires-Dist: uvicorn (>=0.24.0)
Requires-Dist: voyageai (>=0.3.0)
Requires-Dist: watchdog (>=6.0.0)
Project-URL: Documentation, https://github.com/fluffypony/mcp-code-indexer/blob/main/README.md
Project-URL: Homepage, https://github.com/fluffypony/mcp-code-indexer
Project-URL: Repository, https://github.com/fluffypony/mcp-code-indexer
